README.md
setup.cfg
setup.py
pyedmond/__init__.py
pyedmond/_core.cpp
pyedmond/converters.py
pyedmond/core.py
pyedmond.egg-info/PKG-INFO
pyedmond.egg-info/SOURCES.txt
pyedmond.egg-info/dependency_links.txt
pyedmond.egg-info/top_level.txt