Metadata-Version: 1.0
Name: pyedmond
Version: 0.1
Summary: Edmond optimal branching algorithm in C++ wrapped by Python
Home-page: http://github.com/xiaohan2012/pyedmond
Author: Han Xiao
Author-email: xiaohan2012@gmail.com
License: MIT
Platform: UNKNOWN
